_libheif_cffi.abi3.so
pyheif/__init__.py
pyheif/constants.py
pyheif/error.py
pyheif/reader.py
pyheif/transformations.py
pyheif/writer.py
pyheif/data/version.txt
pyheif-0.8.0.dist-info/LICENSE
pyheif-0.8.0.dist-info/METADATA
pyheif-0.8.0.dist-info/WHEEL
pyheif-0.8.0.dist-info/top_level.txt
pyheif-0.8.0.dist-info/RECORD
pyheif.libs/libde265-2445ed64.so.0.1.8
pyheif.libs/libheif-ccb8d375.so.1.18.2
pyheif.libs/libx265-8b3fda8c.so.209
pyheif.libs/libaom-15d86236.so.3.8.3
